Metadata-Version: 1.0
Name: celebrity-births-test-amywinder900
Version: 0.0.1
Summary: Mock package that allows you to find celebrity by date of birth
Home-page: https://github.com/amywinder900/celeb_births
Author: Amy Winder
Author-email: UNKNOWN
License: MIT
Platform: UNKNOWN
